Metadata-Version: 2.1
Name: FacebookAdsLibrary
Version: 1.0.0
Summary: A scraper for getting Ads from Facebook Ads Library
Home-page: https://github.com/faniAhmed/FacebookAdsLibrary
Download-URL: 
Author: Farhan Ahmed
Author-email: jattfarhan10@gmail.com
License: Securely Incorporation
Keywords: Facebook,Library,Transparency,Scraper,API,Ads,Facebook Ads,Ads Library,Facebook Library,Facebook Transparency,Facebook Transparency Scraper,Facebook Ads Library,Facebook Ads Scraper
Platform: any
Classifier: Development Status :: 5 - Production/Stable
Classifier: Environment :: Console
Classifier: Intended Audience :: Developers
Classifier: License :: Free for non-commercial use
Classifier: Natural Language :: Urdu
Classifier: Operating System :: OS Independent
Classifier: Programming Language :: Python :: 3
